{
    "details": {
        "has_opened": true,
        "name": "Oxford St, West One",
        "phone_number": "020 7932 5280"
    },
    "facilities": {
        "seating": "Lots of seats",
        "toilets": "None",
        "wheelchair_access": true,
        "wifi": true
    },
    "location": {
        "address": "Unit G15, West One Shopping Centre, 381 Oxford Street, London W1C 2JS",
        "getting_there": "Within the West One shopping centre, directly above Bond Street tube station.",
        "latitude": "51.514092946",
        "longitude": "-0.149232604637"
    },
    "number": "80",
    "opening_hours": {
        "friday": "06:30 - 22:00",
        "monday": "06:30 - 22:00",
        "saturday": "08:00 - 22:00",
        "sunday": "10:00 - 22:00",
        "thursday": "06:30 - 22:00",
        "tuesday": "06:30 - 22:00",
        "wednesday": "06:30 - 22:00"
    }
}