{
    "details": {
        "has_opened": true,
        "name": "Avery Row",
        "phone_number": "020 7932 5447"
    },
    "facilities": {
        "seating": "Some seats",
        "toilets": "None",
        "wheelchair_access": true,
        "wifi": false
    },
    "location": {
        "address": "32 Avery Row, London W1K 4BE",
        "getting_there": "Exit Bond Street Station and walk to the end of South Molton Street and Avery Row will be in front of you.",
        "latitude": "51.5127038209",
        "longitude": "-0.146015100929"
    },
    "number": "270",
    "opening_hours": {
        "friday": "06:30 - 19:30",
        "monday": "06:30 - 19:30",
        "saturday": "08:30 - 17:30",
        "sunday": "09:30 - 17:30",
        "thursday": "06:30 - 19:30",
        "tuesday": "06:30 - 19:30",
        "wednesday": "06:30 - 19:30"
    }
}