{
    "details": {
        "id": "london-the-walbrook-building",
        "url": "https://locations.pret.co.uk/london/the-walbrook-building",
        "open": true,
        "name": "Cannon Street, The Walbrook",
        "phone_number": "+442079293960",
        "data_last_updated": "2021-10-28T01:56:15.206208"
    },
    "facilities": {
        "seating": true,
        "wheelchair": true,
        "wifi": true
    },
    "location": {
        "street": "The Walbrook Building 95 Cannon Street",
        "city": "London",
        "postal_code": "EC4N 5AE",
        "country": "GB",
        "latitude": "51.511837297509864",
        "longitude": "-0.09043347754902564"
    },
    "opening_hours": {
        "monday": {
            "open": "5:30",
            "close": "19:30",
            "closed": false
        },
        "tuesday": {
            "open": "5:30",
            "close": "19:30",
            "closed": false
        },
        "wednesday": {
            "open": "5:30",
            "close": "19:30",
            "closed": false
        },
        "thursday": {
            "open": "5:30",
            "close": "19:30",
            "closed": false
        },
        "friday": {
            "open": "5:30",
            "close": "19:00",
            "closed": false
        },
        "saturday": {
            "open": "7:00",
            "close": "17:30",
            "closed": false
        },
        "sunday": {
            "open": "7:30",
            "close": "17:00",
            "closed": false
        }
    }
}